pfse_starterkit/__init__.py
pfse_starterkit/__main__.py
pfse_starterkit/sectionproperties_test.py
pfse_starterkit/streamlit_test.py
pfse_starterkit/vtk_cylinder.py
pfse_starterkit-0.4.4.dist-info/entry_points.txt
pfse_starterkit-0.4.4.dist-info/LICENSE
pfse_starterkit-0.4.4.dist-info/WHEEL
pfse_starterkit-0.4.4.dist-info/METADATA
pfse_starterkit-0.4.4.dist-info/RECORD
